pylua_bioxen_vm_lib/__init__.py
pylua_bioxen_vm_lib/cli.py
pylua_bioxen_vm_lib/cli_main.py
pylua_bioxen_vm_lib/env.py
pylua_bioxen_vm_lib/exceptions.py
pylua_bioxen_vm_lib/interactive_session.py
pylua_bioxen_vm_lib/logger.py
pylua_bioxen_vm_lib/lua_process.py
pylua_bioxen_vm_lib/networking.py
pylua_bioxen_vm_lib/ssh_session.py
pylua_bioxen_vm_lib/vm_manager.py
pylua_bioxen_vm_lib/xapi_client.py
pylua_bioxen_vm_lib/xcp_ng_integration.py
pylua_bioxen_vm_lib/utils/__init__.py
pylua_bioxen_vm_lib/utils/curator.py
pylua_bioxen_vm_lib-0.1.22.dist-info/licenses/LICENSE
pylua_bioxen_vm_lib-0.1.22.dist-info/METADATA
pylua_bioxen_vm_lib-0.1.22.dist-info/WHEEL
pylua_bioxen_vm_lib-0.1.22.dist-info/entry_points.txt
pylua_bioxen_vm_lib-0.1.22.dist-info/top_level.txt
pylua_bioxen_vm_lib-0.1.22.dist-info/RECORD
