Metadata-Version: 2.4
Name: pylua_bioxen_vm_lib
Version: 0.1.22
Summary: Process-isolated networked Lua VMs with multi-VM support and XCP-ng integration
Home-page: https://github.com/aptitudetechnology/pylua_bioxen_vm_lib
Author: pylua_bioxen_vm_lib contributors
Author-email: 
Maintainer: pylua_bioxen_vm_lib contributors
License-Expression: MIT
Project-URL: Homepage, https://github.com/aptitudetechnology/pylua_bioxen_vm_lib
Project-URL: Documentation, https://github.com/aptitudetechnology/pylua_bioxen_vm_lib/blob/main/README.md
Project-URL: Repository, https://github.com/aptitudetechnology/pylua_bioxen_vm_lib
Project-URL: Bug Reports, https://github.com/aptitudetechnology/pylua_bioxen_vm_lib/issues
Project-URL: Changelog, https://github.com/aptitudetechnology/pylua_bioxen_vm_lib/blob/main/CHANGELOG.md
Keywords: lua,virtual-machine,bioinformatics,distributed-computing,xcp-ng,bioXen
Classifier: Development Status :: 4 - Beta
Classifier: Intended Audience :: Developers
Classifier: Intended Audience :: Science/Research
Classifier: Topic :: Scientific/Engineering :: Bio-Informatics
Classifier: Topic :: Software Development :: Libraries :: Python Modules
Classifier: Topic :: System :: Distributed Computing
Classifier: Programming Language :: Python :: 3
Classifier: Programming Language :: Python :: 3.7
Classifier: Programming Language :: Python :: 3.8
Classifier: Programming Language :: Python :: 3.9
Classifier: Programming Language :: Python :: 3.10
Classifier: Programming Language :: Python :: 3.11
Classifier: Programming Language :: Lua
Classifier: Operating System :: OS Independent
Requires-Python: >=3.7
License-File: LICENSE
Requires-Dist: requests>=2.25.0
Requires-Dist: paramiko>=2.7.0
Requires-Dist: urllib3>=1.26.0
Requires-Dist: questionary>=1.10.0
Provides-Extra: dev
Requires-Dist: pytest>=6.0; extra == "dev"
Requires-Dist: pytest-asyncio; extra == "dev"
Requires-Dist: black; extra == "dev"
Requires-Dist: flake8; extra == "dev"
Requires-Dist: mypy; extra == "dev"
Provides-Extra: xcpng
Requires-Dist: requests>=2.31.0; extra == "xcpng"
Requires-Dist: paramiko>=3.0.0; extra == "xcpng"
Dynamic: license-file
